allaccess/__init__.py
allaccess/admin.py
allaccess/apps.py
allaccess/backends.py
allaccess/clients.py
allaccess/compat.py
allaccess/context_processors.py
allaccess/fields.py
allaccess/models.py
allaccess/urls.py
allaccess/views.py
allaccess/fixtures/common_providers.json
allaccess/migrations/0001_initial.py
allaccess/migrations/0002_auto_20150511_1853.py
allaccess/migrations/__init__.py
allaccess/tests/__init__.py
allaccess/tests/base.py
allaccess/tests/test_backends.py
allaccess/tests/test_clients.py
allaccess/tests/test_context_processors.py
allaccess/tests/test_models.py
allaccess/tests/test_views.py
allaccess/tests/urls.py
allaccess/tests/custom/__init__.py
allaccess/tests/custom/models.py
allaccess/tests/custom/tests.py
allaccess/tests/custom/urls.py
allaccess/tests/custom/views.py
django_all_access-0.9.0.dist-info/DESCRIPTION.rst
django_all_access-0.9.0.dist-info/METADATA
django_all_access-0.9.0.dist-info/RECORD
django_all_access-0.9.0.dist-info/WHEEL
django_all_access-0.9.0.dist-info/metadata.json
django_all_access-0.9.0.dist-info/top_level.txt
