Metadata-Version: 1.1
Name: django-all-access
Version: 0.9.0
Summary: django-all-access is a reusable application for user registration and authentication from OAuth 1.0 and OAuth 2.0 providers such as Twitter and Facebook.
Home-page: https://github.com/mlavin/django-all-access
Author: Mark Lavin
Author-email: markdlavin@gmail.com
License: BSD
Platform: UNKNOWN
Classifier: Development Status :: 4 - Beta
Classifier: Intended Audience :: Developers
Classifier: Framework :: Django
Classifier: Framework :: Django :: 1.8
Classifier: Framework :: Django :: 1.9
Classifier: Framework :: Django :: 1.10
Classifier: License :: OSI Approved :: BSD License
Classifier: Operating System :: OS Independent
Classifier: Programming Language :: Python
Classifier: Programming Language :: Python :: 2
Classifier: Programming Language :: Python :: 2.7
Classifier: Programming Language :: Python :: 3
Classifier: Programming Language :: Python :: 3.3
Classifier: Programming Language :: Python :: 3.4
Classifier: Programming Language :: Python :: 3.5
Classifier: Topic :: Internet :: WWW/HTTP :: Dynamic Content
Classifier: Topic :: Software Development :: Libraries :: Python Modules
